kpm/__init__.py
kpm/auth.py
kpm/console.py
kpm/display.py
kpm/exception.py
kpm/loghandler.py
kpm/manifest.py
kpm/manifest_chart.py
kpm/manifest_jsonnet.py
kpm/new.py
kpm/packager.py
kpm/registry.py
kpm/render_jsonnet.py
kpm/template_filters.py
kpm/utils.py
kpm/api/__init__.py
kpm/api/app.py
kpm/api/builder.py
kpm/api/config.py
kpm/api/deployment.py
kpm/api/info.py
kpm/api/wsgi.py
kpm/api/impl/__init__.py
kpm/api/impl/builder.py
kpm/commands/__init__.py
kpm/commands/cli.py
kpm/commands/command_base.py
kpm/commands/deploy.py
kpm/commands/generate.py
kpm/commands/jsonnet.py
kpm/commands/kexec.py
kpm/commands/new.py
kpm/commands/push.py
kpm/commands/remove.py
kpm/commands/version.py
kpm/convert/__init__.py
kpm/convert/kompose.py
kpm/formats/__init__.py
kpm/formats/chart.py
kpm/formats/kub.py
kpm/formats/kub_base.py
kpm/formats/kubcompose.py
kpm/formats/kubcomposetokub.py
kpm/jsonnet/manifest.jsonnet.j2
kpm/jsonnet/lib/kpm-utils.libjsonnet
kpm/jsonnet/lib/kpm.libjsonnet
kpm/platforms/__init__.py
kpm/platforms/dockercompose.py
kpm/platforms/helm.py
kpm/platforms/kubernetes.py
kpm-0.25.0.data/scripts/kpm
kpm-0.25.0.dist-info/DESCRIPTION.rst
kpm-0.25.0.dist-info/METADATA
kpm-0.25.0.dist-info/RECORD
kpm-0.25.0.dist-info/WHEEL
kpm-0.25.0.dist-info/metadata.json
kpm-0.25.0.dist-info/top_level.txt
