Metadata-Version: 2.0
Name: kpm
Version: 0.25.0
Summary: KPM cli
Home-page: https://github.com/coreos/kpm
Author: Antoine Legrand
Author-email: 2t.antoine@gmail.com
License: Apache License version 2
Keywords: kpm,kpmpy,kubernetes
Platform: UNKNOWN
Classifier: Development Status :: 2 - Pre-Alpha
Classifier: Intended Audience :: Developers
Classifier: Natural Language :: English
Classifier: Programming Language :: Python :: 2
Classifier: Programming Language :: Python :: 2.7
Requires-Dist: appr (>=0.5)
Requires-Dist: futures
Requires-Dist: requests (>=2.11.1)
Requires-Dist: pyyaml
Requires-Dist: jinja2 (>=2.8)
Requires-Dist: jsonpatch
Requires-Dist: tabulate
Requires-Dist: termcolor
Requires-Dist: python-etcd
Requires-Dist: semantic-version (>=2.6.0)
Requires-Dist: flask
Requires-Dist: Flask (>=0.10.1)
Requires-Dist: flask-cors
Requires-Dist: jsonnet (>=0.9.0)
Provides-Extra: secure
Requires-Dist: ecdsa; extra == 'secure'
Requires-Dist: cryptography; extra == 'secure'
Requires-Dist: urllib3[secure]; extra == 'secure'
